psycopg2_connection/__init__.py
psycopg2_connection/psycopg2_connection.py
psycopg2_connection-0.1.1.1.dist-info/METADATA
psycopg2_connection-0.1.1.1.dist-info/WHEEL
psycopg2_connection-0.1.1.1.dist-info/top_level.txt
psycopg2_connection-0.1.1.1.dist-info/RECORD
