Metadata-Version: 2.1
Name: psycopg2-connection
Version: 0.1.1.1
Summary: Abstract away common patterns you might use in psycopg2.
Home-page: https://github.com/ethancarlsson/psycopg2-mini-abstractions
Author: Ethan Carlsson
Author-email: ethanmcarlsson@gmail.com
License: MIT
Platform: UNKNOWN
Classifier: License :: OSI Approved :: MIT License
Classifier: Programming Language :: Python :: 3
Classifier: Programming Language :: Python :: 3.8
